harmonyai/__init__.py
harmonyai/main.py
harmonyaif-1.0.2.dist-info/METADATA
harmonyaif-1.0.2.dist-info/WHEEL
harmonyaif-1.0.2.dist-info/top_level.txt
harmonyaif-1.0.2.dist-info/RECORD
