Metadata-Version: 2.1
Name: harmonyaif
Version: 1.0.2
Summary: Harmony ai is a simple conversational chatbot
Author: saikrishnak
Classifier: Programming Language :: Python :: 3
Classifier: License :: OSI Approved :: MIT License
Classifier: Operating System :: OS Independent
Requires-Dist: SpeechRecognition
Requires-Dist: pygame
Requires-Dist: gTTS
Requires-Dist: beautifulsoup4
Requires-Dist: spotipy
Requires-Dist: requests
Requires-Dist: pyaudio
Requires-Dist: distutils-pytest
Requires-Dist: pycaw
Requires-Dist: comtypes
